youdao/__init__.py
youdao/cmd.py
youdao/config.py
youdao/customizer.py
youdao/query.py
youdao/racer.py
youdao/serve.py
youdao/spider.py
youdao/storage.py
youdaodict-6.1.1.dist-info/LICENSE
youdaodict-6.1.1.dist-info/METADATA
youdaodict-6.1.1.dist-info/WHEEL
youdaodict-6.1.1.dist-info/entry_points.txt
youdaodict-6.1.1.dist-info/top_level.txt
youdaodict-6.1.1.dist-info/RECORD
