Metadata-Version: 2.2
Name: YoudaoDict
Version: 6.1.1
Summary: 通过有道爬虫查询单词
Author: hellflame
License: MIT
Project-URL: Homepage, https://github.com/hellflame/youdao
Project-URL: Repository, https://github.com/hellflame/youdao
Project-URL: Issues, https://github.com/hellflame/youdao/issues
Project-URL: Changelog, https://github.com/hellflame/youdao?tab=readme-ov-file#%E5%BC%80%E5%8F%91%E5%8E%86%E7%A8%8B
Keywords: 有道,翻译,youdao,crawler,spider
Classifier: Development Status :: 5 - Production/Stable
Classifier: Intended Audience :: Developers
Classifier: License :: OSI Approved :: MIT License
Classifier: Programming Language :: Python :: 3.9
Classifier: Environment :: Console
Classifier: Operating System :: MacOS :: MacOS X
Classifier: Operating System :: POSIX
Requires-Python: >=3.9
License-File: LICENSE
Requires-Dist: bs4
Requires-Dist: httpx
Requires-Dist: aiosqlite
